lp_tool_mcp/__init__.py
lp_tool_mcp/app.py
lp_tool_mcp-0.1.2.dist-info/METADATA
lp_tool_mcp-0.1.2.dist-info/WHEEL
lp_tool_mcp-0.1.2.dist-info/entry_points.txt
lp_tool_mcp-0.1.2.dist-info/RECORD
