Metadata-Version: 2.4
Name: lp-tool-mcp
Version: 0.1.2
Summary: lp tool mcp
Requires-Python: >=3.11
Requires-Dist: fastmcp>=2.3.5
Requires-Dist: psutil>=7.0.0
